django_audimatic/__init__.py
django_audimatic/admin.py
django_audimatic/apps.py
django_audimatic/models.py
django_audimatic/views.py
django_audimatic/acceptance/__init__.py
django_audimatic/acceptance/environment.py
django_audimatic/acceptance/steps/__init__.py
django_audimatic/acceptance/steps/given.py
django_audimatic/acceptance/steps/then.py
django_audimatic/acceptance/steps/when.py
django_audimatic/migrations/0001_initial.py
django_audimatic/migrations/__init__.py
django_audimatic-0.4.0.dist-info/METADATA
django_audimatic-0.4.0.dist-info/WHEEL
django_audimatic-0.4.0.dist-info/licenses/LICENSE
django_audimatic-0.4.0.dist-info/RECORD
